ruleify/__init__.py
ruleify-0.0.1.dist-info/LICENSE
ruleify-0.0.1.dist-info/METADATA
ruleify-0.0.1.dist-info/WHEEL
ruleify-0.0.1.dist-info/top_level.txt
ruleify-0.0.1.dist-info/RECORD
