Metadata-Version: 2.1
Name: ruleify
Version: 0.0.1
Summary: A python rules engine
Home-page: https://github.com/unai/ruleify
Author: Unai Ltd
Author-email: ruleify@unai.com
License: UNKNOWN
Platform: UNKNOWN
Classifier: Programming Language :: Python :: 3
Classifier: License :: Other/Proprietary License
Classifier: Operating System :: OS Independent
Requires-Python: >=3.6
